README.txt
setup.py
bestappever/__init__.py
bestappever/models.py
bestappever/run.py
bestappever/tests.py
bestappever/views.py
bestappever.egg-info/PKG-INFO
bestappever.egg-info/SOURCES.txt
bestappever.egg-info/dependency_links.txt
bestappever.egg-info/entry_points.txt
bestappever.egg-info/not-zip-safe
bestappever.egg-info/requires.txt
bestappever.egg-info/top_level.txt