Metadata-Version: 1.0
Name: bestappever
Version: 0.1
Summary: An example application which uses repoze.bfg
Home-page: http://mrtopf.de/blog/tutorials/a-first-look-at-repozebfg/
Author: Christian Scholz
Author-email: cs@comlounge.net
License: UNKNOWN
Keywords: web wsgi bfg zope example
Platform: UNKNOWN
Classifier: Development Status :: 3 - Alpha
Classifier: Intended Audience :: Developers
Classifier: Programming Language :: Python
Classifier: Topic :: Internet :: WWW/HTTP
Classifier: Topic :: Internet :: WWW/HTTP :: Dynamic Content
Classifier: Topic :: Internet :: WWW/HTTP :: WSGI
Classifier: Topic :: Internet :: WWW/HTTP :: WSGI :: Application
